pyunit_string/__init__.py
pyunit_string/strings.py
pyunit_string-2020.4.10.dist-info/METADATA
pyunit_string-2020.4.10.dist-info/WHEEL
pyunit_string-2020.4.10.dist-info/top_level.txt
pyunit_string-2020.4.10.dist-info/RECORD
