Metadata-Version: 2.1
Name: pyunit-string
Version: 2020.4.10
Summary: 对python字符串str中的一些方法在抽象、在加强一些。让字符串操作使用起来更加方面
Home-page: https://github.com/PyUnit/pyunit_string
Author: Jtyoui
Author-email: jtyoui@qq.com
License: MIT Licence
Platform: any
Classifier: Programming Language :: Python :: 3
Classifier: License :: OSI Approved :: MIT License
Classifier: Operating System :: OS Independent
